compose/__init__.py
compose/__main__.py
compose/const.py
compose/container.py
compose/errors.py
compose/network.py
compose/parallel.py
compose/progress_stream.py
compose/project.py
compose/service.py
compose/timeparse.py
compose/utils.py
compose/version.py
compose/volume.py
compose/cli/__init__.py
compose/cli/colors.py
compose/cli/command.py
compose/cli/docker_client.py
compose/cli/docopt_command.py
compose/cli/errors.py
compose/cli/formatter.py
compose/cli/log_printer.py
compose/cli/main.py
compose/cli/signals.py
compose/cli/utils.py
compose/cli/verbose_proxy.py
compose/config/__init__.py
compose/config/compose_spec.json
compose/config/config.py
compose/config/config_schema_v1.json
compose/config/environment.py
compose/config/errors.py
compose/config/interpolation.py
compose/config/serialize.py
compose/config/sort_services.py
compose/config/types.py
compose/config/validation.py
compose/metrics/__init__.py
compose/metrics/client.py
compose/metrics/decorator.py
valory_docker_compose-1.29.3.dist-info/LICENSE
valory_docker_compose-1.29.3.dist-info/METADATA
valory_docker_compose-1.29.3.dist-info/WHEEL
valory_docker_compose-1.29.3.dist-info/entry_points.txt
valory_docker_compose-1.29.3.dist-info/top_level.txt
valory_docker_compose-1.29.3.dist-info/RECORD
