Metadata-Version: 2.1
Name: valory-docker-compose
Version: 1.29.3
Summary: Multi-container orchestration for Docker
Home-page: https://www.docker.com/
Author: Docker, Inc.
License: Apache License 2.0
Project-URL: Documentation, https://docs.docker.com/compose/overview
Project-URL: Changelog, https://github.com/docker/compose/blob/release/CHANGELOG.md
Project-URL: Source, https://github.com/docker/compose
Project-URL: Tracker, https://github.com/docker/compose/issues
Classifier: Development Status :: 5 - Production/Stable
Classifier: Environment :: Console
Classifier: Intended Audience :: Developers
Classifier: License :: OSI Approved :: Apache Software License
Classifier: Programming Language :: Python :: 3
Classifier: Programming Language :: Python :: 3.4
Classifier: Programming Language :: Python :: 3.6
Classifier: Programming Language :: Python :: 3.7
Classifier: Programming Language :: Python :: 3.8
Classifier: Programming Language :: Python :: 3.9
Requires-Python: >=3.4
Provides-Extra: socks
Provides-Extra: tests
License-File: LICENSE
